tuitka/__init__.py
tuitka/__main__.py
tuitka/constants.py
tuitka/inline_app.py
tuitka/tui.py
tuitka/utils.py
tuitka/assets/__init__.py
tuitka/assets/style.tcss
tuitka/assets/style_inline_app.tcss
tuitka/assets/style_modal_compilation.tcss
tuitka/assets/style_modal_filedialog.tcss
tuitka/assets/style_modal_settings.tcss
tuitka/assets/style_modal_splashscreen.tcss
tuitka/assets/style_modal_support.tcss
tuitka/assets/content/__init__.py
tuitka/assets/content/commercial.md
tuitka/assets/content/support_nuitka.md
tuitka/assets/logo/nuitka.png
tuitka/widgets/compilation_status.py
tuitka/widgets/nuitka_header.py
tuitka/widgets/script_input.py
tuitka/widgets/modals/__init__.py
tuitka/widgets/modals/compilation.py
tuitka/widgets/modals/file_dialog.py
tuitka/widgets/modals/settings.py
tuitka/widgets/modals/settings_widgets.py
tuitka/widgets/modals/splash.py
tuitka/widgets/modals/support.py
tuitka-0.1.0.dist-info/METADATA
tuitka-0.1.0.dist-info/WHEEL
tuitka-0.1.0.dist-info/entry_points.txt
tuitka-0.1.0.dist-info/RECORD
