Metadata-Version: 2.4
Name: tuitka
Version: 0.1.0
Summary: A TUI Frontend for Nuitka - The Python Compiler
Project-URL: Homepage, https://github.com/Nuitka/Tuitka
Project-URL: Repository, https://github.com/Nuitka/Tuitka.git
Author-email: KRRT7 <turcioskevinr@gmail.com>, Zaloog <gramslars@gmail.com>
Requires-Python: >=3.10
Requires-Dist: nuitka>=2.7.7
Requires-Dist: pywinpty<3; sys_platform == 'win32'
Requires-Dist: rich-pixels>=3.0.1
Requires-Dist: textual-tty>=0.2.2
Requires-Dist: textual-window
Requires-Dist: textual>=3.2.0
Requires-Dist: toml>=0.10.2
Requires-Dist: uv>=0.7.3
